Workbook

Sheet Resumen
A1: PANEL DE CONTROL — PRUEBAS DE ACCESO A SISTEMAS
A2: SAP E01 · Todos los indicadores se calculan a partir de la hoja «Seguimiento» y se actualizan solos al editarla
B4: =COUNTA(Seguimiento!$B$7:$B$33) -> 17 | F4: =COUNTIF(Seguimiento!$F$7:$F$33,"Probado") -> 14 | J4: =COUNTA(Seguimiento!$B$7:$B$33)-COUNTIF(Seguimiento!$F$7:$F$33,"Probado")-COUNTIF(Seguimiento!$F$7:$F$33,"No aplica") -> 3 | N4: =IFERROR(COUNTIF(Seguimiento!$F$7:$F$33,"Probado")/MAX(1,COUNTA(Seguimiento!$B$7:$B$33)-COUNTIF(Seguimiento!$F$7:$F$33,"No aplica")),0) -> 0.82352941
B5: SISTEMAS EN SEGUIMIENTO | F5: YA PROBADOS | J5: PENDIENTES DE PROBAR | N5: % DE AVANCE DE LAS PRUEBAS
B7: =COUNTIF(Seguimiento!$I$7:$I$33,"Acceso total (WiFi + Cable)") -> 6 | F7: =COUNTIF(Seguimiento!$I$7:$I$33,"Solo WiFi")+COUNTIF(Seguimiento!$I$7:$I$33,"Solo cable Ethernet") -> 1 | J7: =COUNTIF(Seguimiento!$I$7:$I$33,"Sin acceso") -> 7 | N7: =COUNTIFS(Seguimiento!$J$7:$J$33,"Crítica",Seguimiento!$I$7:$I$33,"<>Acceso total (WiFi + Cable)",Seguimiento!$B$7:$B$33,"<>") -> 2
B8: ACCESO TOTAL (WIFI + CABLE) | F8: ACCESO LIMITADO (UN SOLO MEDIO) | J8: SIN ACCESO | N8: CRÍTICOS SIN ACCESO COMPLETO
B10: DISTRIBUCIÓN POR RESULTADO DE CONECTIVIDAD
B11: Resultado de conectividad | E11: Sistemas | F11: % del total
B12: Acceso total (WiFi + Cable) | E12: =COUNTIF(Seguimiento!$I$7:$I$33,$B12) -> 6 | F12: =IFERROR($E12/$E$18,0) -> 0.35294118
B13: Solo WiFi | E13: =COUNTIF(Seguimiento!$I$7:$I$33,$B13) -> 1 | F13: =IFERROR($E13/$E$18,0) -> 0.058823529
B14: Solo cable Ethernet | E14: =COUNTIF(Seguimiento!$I$7:$I$33,$B14) -> 0 | F14: =IFERROR($E14/$E$18,0) -> 0
B15: Sin acceso | E15: =COUNTIF(Seguimiento!$I$7:$I$33,$B15) -> 7 | F15: =IFERROR($E15/$E$18,0) -> 0.41176471
B16: Pendiente | E16: =COUNTIF(Seguimiento!$I$7:$I$33,$B16) -> 3 | F16: =IFERROR($E16/$E$18,0) -> 0.17647059
B17: No aplica | E17: =COUNTIF(Seguimiento!$I$7:$I$33,$B17) -> 0 | F17: =IFERROR($E17/$E$18,0) -> 0
B18: TOTAL | E18: =SUM(E12:E17) -> 17 | F18: =IFERROR($E18/$E18,0) -> 1
B24: DISTRIBUCIÓN POR ÁREA FUNCIONAL
B25: Área funcional | E25: Sistemas | F25: Acceso total | G25: Acceso limitado | H25: Sin acceso | I25: Pendiente
B26: SAP E01 / ERP | E26: =COUNTIF(Seguimiento!$C$7:$C$33,$B26) -> 1 | F26: =COUNTIFS(Seguimiento!$C$7:$C$33,$B26,Seguimiento!$I$7:$I$33,"Acceso total (WiFi + Cable)") -> 0 | G26: =COUNTIFS(Seguimiento!$C$7:$C$33,$B26,Seguimiento!$I$7:$I$33,"Solo WiFi")+COUNTIFS(Seguimiento!$C$7:$C$33,$B26,Seguimiento!$I$7:$I$33,"Solo cable Ethernet") -> 0 | H26: =COUNTIFS(Seguimiento!$C$7:$C$33,$B26,Seguimiento!$I$7:$I$33,"Sin acceso") -> 0 | I26: =COUNTIFS(Seguimiento!$C$7:$C$33,$B26,Seguimiento!$I$7:$I$33,"Pendiente") -> 1
B27: WITRON / CPMS | E27: =COUNTIF(Seguimiento!$C$7:$C$33,$B27) -> 1 | F27: =COUNTIFS(Seguimiento!$C$7:$C$33,$B27,Seguimiento!$I$7:$I$33,"Acceso total (WiFi + Cable)") -> 0 | G27: =COUNTIFS(Seguimiento!$C$7:$C$33,$B27,Seguimiento!$I$7:$I$33,"Solo WiFi")+COUNTIFS(Seguimiento!$C$7:$C$33,$B27,Seguimiento!$I$7:$I$33,"Solo cable Ethernet") -> 1 | H27: =COUNTIFS(Seguimiento!$C$7:$C$33,$B27,Seguimiento!$I$7:$I$33,"Sin acceso") -> 0 | I27: =COUNTIFS(Seguimiento!$C$7:$C$33,$B27,Seguimiento!$I$7:$I$33,"Pendiente") -> 0
B28: CARPA | E28: =COUNTIF(Seguimiento!$C$7:$C$33,$B28) -> 2 | F28: =COUNTIFS(Seguimiento!$C$7:$C$33,$B28,Seguimiento!$I$7:$I$33,"Acceso total (WiFi + Cable)") -> 0 | G28: =COUNTIFS(Seguimiento!$C$7:$C$33,$B28,Seguimiento!$I$7:$I$33,"Solo WiFi")+COUNTIFS(Seguimiento!$C$7:$C$33,$B28,Seguimiento!$I$7:$I$33,"Solo cable Ethernet") -> 0 | H28: =COUNTIFS(Seguimiento!$C$7:$C$33,$B28,Seguimiento!$I$7:$I$33,"Sin acceso") -> 2 | I28: =COUNTIFS(Seguimiento!$C$7:$C$33,$B28,Seguimiento!$I$7:$I$33,"Pendiente") -> 0
B29: Cuentas a pagar (Matchpay) | E29: =COUNTIF(Seguimiento!$C$7:$C$33,$B29) -> 7 | F29: =COUNTIFS(Seguimiento!$C$7:$C$33,$B29,Seguimiento!$I$7:$I$33,"Acceso total (WiFi + Cable)") -> 2 | G29: =COUNTIFS(Seguimiento!$C$7:$C$33,$B29,Seguimiento!$I$7:$I$33,"Solo WiFi")+COUNTIFS(Seguimiento!$C$7:$C$33,$B29,Seguimiento!$I$7:$I$33,"Solo cable Ethernet") -> 0 | H29: =COUNTIFS(Seguimiento!$C$7:$C$33,$B29,Seguimiento!$I$7:$I$33,"Sin acceso") -> 5 | I29: =COUNTIFS(Seguimiento!$C$7:$C$33,$B29,Seguimiento!$I$7:$I$33,"Pendiente") -> 0
B30: Facturación electrónica | E30: =COUNTIF(Seguimiento!$C$7:$C$33,$B30) -> 2 | F30: =COUNTIFS(Seguimiento!$C$7:$C$33,$B30,Seguimiento!$I$7:$I$33,"Acceso total (WiFi + Cable)") -> 1 | G30: =COUNTIFS(Seguimiento!$C$7:$C$33,$B30,Seguimiento!$I$7:$I$33,"Solo WiFi")+COUNTIFS(Seguimiento!$C$7:$C$33,$B30,Seguimiento!$I$7:$I$33,"Solo cable Ethernet") -> 0 | H30: =COUNTIFS(Seguimiento!$C$7:$C$33,$B30,Seguimiento!$I$7:$I$33,"Sin acceso") -> 0 | I30: =COUNTIFS(Seguimiento!$C$7:$C$33,$B30,Seguimiento!$I$7:$I$33,"Pendiente") -> 1
B31: Ofimática y colaboración | E31: =COUNTIF(Seguimiento!$C$7:$C$33,$B31) -> 3 | F31: =COUNTIFS(Seguimiento!$C$7:$C$33,$B31,Seguimiento!$I$7:$I$33,"Acceso total (WiFi + Cable)") -> 3 | G31: =COUNTIFS(Seguimiento!$C$7:$C$33,$B31,Seguimiento!$I$7:$I$33,"Solo WiFi")+COUNTIFS(Seguimiento!$C$7:$C$33,$B31,Seguimiento!$I$7:$I$33,"Solo cable Ethernet") -> 0 | H31: =COUNTIFS(Seguimiento!$C$7:$C$33,$B31,Seguimiento!$I$7:$I$33,"Sin acceso") -> 0 | I31: =COUNTIFS(Seguimiento!$C$7:$C$33,$B31,Seguimiento!$I$7:$I$33,"Pendiente") -> 0
B32: Escritorio remoto | E32: =COUNTIF(Seguimiento!$C$7:$C$33,$B32) -> 1 | F32: =COUNTIFS(Seguimiento!$C$7:$C$33,$B32,Seguimiento!$I$7:$I$33,"Acceso total (WiFi + Cable)") -> 0 | G32: =COUNTIFS(Seguimiento!$C$7:$C$33,$B32,Seguimiento!$I$7:$I$33,"Solo WiFi")+COUNTIFS(Seguimiento!$C$7:$C$33,$B32,Seguimiento!$I$7:$I$33,"Solo cable Ethernet") -> 0 | H32: =COUNTIFS(Seguimiento!$C$7:$C$33,$B32,Seguimiento!$I$7:$I$33,"Sin acceso") -> 0 | I32: =COUNTIFS(Seguimiento!$C$7:$C$33,$B32,Seguimiento!$I$7:$I$33,"Pendiente") -> 1
B33: TOTAL | E33: =SUM(E26:E32) -> 17 | F33: =SUM(F26:F32) -> 6 | G33: =SUM(G26:G32) -> 1 | H33: =SUM(H26:H32) -> 7 | I33: =SUM(I26:I32) -> 3
B34: =IF($E$33=COUNTA(Seguimiento!$B$7:$B$33),"Todas las áreas cuadran con la hoja Seguimiento.","Atención: hay sistemas cuya Área funcional no coincide con ninguna fila de esta tabla. Añada el área que falte para que el total vuelva a cuadrar.") -> Todas las áreas cuadran con la hoja Seguimiento.
B38: PRÓXIMAS ACCIONES
B39: Próxima acción | E39: Sistemas | F39: De los cuales, críticos o de prioridad alta
B40: Ninguna | E40: =COUNTIF(Seguimiento!$M$7:$M$33,$B40) -> 6 | F40: =COUNTIFS(Seguimiento!$M$7:$M$33,$B40,Seguimiento!$J$7:$J$33,"Crítica")+COUNTIFS(Seguimiento!$M$7:$M$33,$B40,Seguimiento!$J$7:$J$33,"Alta") -> 3
B41: Programar prueba | E41: =COUNTIF(Seguimiento!$M$7:$M$33,$B41) -> 1 | F41: =COUNTIFS(Seguimiento!$M$7:$M$33,$B41,Seguimiento!$J$7:$J$33,"Crítica")+COUNTIFS(Seguimiento!$M$7:$M$33,$B41,Seguimiento!$J$7:$J$33,"Alta") -> 1
B42: Instalar / Configurar | E42: =COUNTIF(Seguimiento!$M$7:$M$33,$B42) -> 2 | F42: =COUNTIFS(Seguimiento!$M$7:$M$33,$B42,Seguimiento!$J$7:$J$33,"Crítica")+COUNTIFS(Seguimiento!$M$7:$M$33,$B42,Seguimiento!$J$7:$J$33,"Alta") -> 2
B43: Solicitar acceso a IT | E43: =COUNTIF(Seguimiento!$M$7:$M$33,$B43) -> 7 | F43: =COUNTIFS(Seguimiento!$M$7:$M$33,$B43,Seguimiento!$J$7:$J$33,"Crítica")+COUNTIFS(Seguimiento!$M$7:$M$33,$B43,Seguimiento!$J$7:$J$33,"Alta") -> 5
B44: Escalar a IT / Redes | E44: =COUNTIF(Seguimiento!$M$7:$M$33,$B44) -> 1 | F44: =COUNTIFS(Seguimiento!$M$7:$M$33,$B44,Seguimiento!$J$7:$J$33,"Crítica")+COUNTIFS(Seguimiento!$M$7:$M$33,$B44,Seguimiento!$J$7:$J$33,"Alta") -> 1
B45: Revisar VPN / Firewall | E45: =COUNTIF(Seguimiento!$M$7:$M$33,$B45) -> 0 | F45: =COUNTIFS(Seguimiento!$M$7:$M$33,$B45,Seguimiento!$J$7:$J$33,"Crítica")+COUNTIFS(Seguimiento!$M$7:$M$33,$B45,Seguimiento!$J$7:$J$33,"Alta") -> 0
B46: Reprogramar prueba | E46: =COUNTIF(Seguimiento!$M$7:$M$33,$B46) -> 0 | F46: =COUNTIFS(Seguimiento!$M$7:$M$33,$B46,Seguimiento!$J$7:$J$33,"Crítica")+COUNTIFS(Seguimiento!$M$7:$M$33,$B46,Seguimiento!$J$7:$J$33,"Alta") -> 0
B47: En seguimiento | E47: =COUNTIF(Seguimiento!$M$7:$M$33,$B47) -> 0 | F47: =COUNTIFS(Seguimiento!$M$7:$M$33,$B47,Seguimiento!$J$7:$J$33,"Crítica")+COUNTIFS(Seguimiento!$M$7:$M$33,$B47,Seguimiento!$J$7:$J$33,"Alta") -> 0
B48: TOTAL | E48: =SUM(E40:E47) -> 17 | F48: =SUM(F40:F47) -> 12
B50: • Fuente: listado «SAP E01 – Pendiente de prueba» facilitado por el usuario. Los resultados de WiFi y de cable Ethernet reproducen literalmente ese listado.
B51: • La columna «Criticidad» de la hoja «Seguimiento» es una propuesta inicial y no venía en el listado de origen: revísela antes de usarla para priorizar.
B52: • Ningún indicador de esta hoja está escrito a mano: todos son fórmulas COUNTIF/COUNTIFS sobre la hoja «Seguimiento» (filas 7 a 33, con margen para dar de alta sistemas nuevos).

Sheet Seguimiento
A1: SEGUIMIENTO DE PRUEBAS DE ACCESO A SISTEMAS
A2: SAP E01 · Validación de conectividad desde la red de DS Smith — WiFi vs. cable Ethernet
A3: CÓMO USAR ESTA HOJA: rellene únicamente las celdas de fondo crema — «Estado de la prueba», «WiFi», «Cable Ethernet», «Criticidad», «Responsable», «Fecha de prueba», «Próxima acción» y «Observaciones» —, todas ellas con desplegable salvo las de texto libre y la fecha. La columna «Resultado de conectividad» se calcula sola y no debe editarse. Las filas vacías del final están listas para añadir sistemas nuevos: se contabilizan solas en la hoja «Resumen».
A4: ■ Acceso total | C4: ■ Solo WiFi / solo cable | E4: ■ Sin acceso | G4: ■ Pendiente | I4: ■ En curso | K4: ■ Celdas a rellenar (fondo crema)
A6: N.º | B6: Sistema / Aplicación | C6: Área funcional | D6: Ámbito geográfico | E6: URL / Vía de acceso | F6: Estado de la prueba | G6: WiFi | H6: Cable Ethernet | I6: Resultado de conectividad | J6: Criticidad | K6: Responsable | L6: Fecha de prueba | M6: Próxima acción | N6: Observaciones
A7: 1 | B7: AS400 | C7: SAP E01 / ERP | D7: España (Las Palmas y Tenerife), Francia e Italia | E7: Cliente / emulador AS400 | F7: Pendiente de prueba | G7: No probado | H7: No probado | I7: =IF($B7="","",IF($F7="No aplica","No aplica",IF(AND($G7="OK",$H7="OK"),"Acceso total (WiFi + Cable)",IF(AND($G7="OK",$H7<>"OK"),"Solo WiFi",IF(AND($H7="OK",$G7<>"OK"),"Solo cable Ethernet",IF(AND($G7="KO",$H7="KO"),"Sin acceso","Pendiente")))))) -> Pendiente | J7: Crítica | M7: Programar prueba | N7: Pendiente de probar en las tres geografías (España, Francia e Italia).
A8: 2 | B8: Citrix — acceso a WITRON | C8: WITRON / CPMS | D8: España, Italia y Francia | E8: https://ipstorefront.ipaper.com/ | F8: Probado | G8: OK | H8: KO | I8: =IF($B8="","",IF($F8="No aplica","No aplica",IF(AND($G8="OK",$H8="OK"),"Acceso total (WiFi + Cable)",IF(AND($G8="OK",$H8<>"OK"),"Solo WiFi",IF(AND($H8="OK",$G8<>"OK"),"Solo cable Ethernet",IF(AND($G8="KO",$H8="KO"),"Sin acceso","Pendiente")))))) -> Solo WiFi | J8: Crítica | M8: Escalar a IT / Redes | N8: Probado con éxito mediante WiFi. Por cable Ethernet no funciona (WITRON/CPMS — España).
A9: 3 | B9: Sage — acceso a Adonix (CARPA) | C9: CARPA | D9: España (CARPA) | E9: http://ub99sagep03:8124/auth/login/page | F9: Probado | G9: KO | H9: KO | I9: =IF($B9="","",IF($F9="No aplica","No aplica",IF(AND($G9="OK",$H9="OK"),"Acceso total (WiFi + Cable)",IF(AND($G9="OK",$H9<>"OK"),"Solo WiFi",IF(AND($H9="OK",$G9<>"OK"),"Solo cable Ethernet",IF(AND($G9="KO",$H9="KO"),"Sin acceso","Pendiente")))))) -> Sin acceso | J9: Alta | M9: Solicitar acceso a IT | N9: Sin acceso desde la red de DS Smith, ni por WiFi ni por cable. En el listado original aparecía duplicado (bloques 1 y 2) con el mismo resultado; se ha consolidado en esta única fila.
A10: 4 | B10: SharePoint / OneDrive IP | C10: Ofimática y colaboración | D10: Global | E10: https://ipapercloud.sharepoint.com/ | F10: Probado | G10: OK | H10: OK | I10: =IF($B10="","",IF($F10="No aplica","No aplica",IF(AND($G10="OK",$H10="OK"),"Acceso total (WiFi + Cable)",IF(AND($G10="OK",$H10<>"OK"),"Solo WiFi",IF(AND($H10="OK",$G10<>"OK"),"Solo cable Ethernet",IF(AND($G10="KO",$H10="KO"),"Sin acceso","Pendiente")))))) -> Acceso total (WiFi + Cable) | J10: Media | M10: Ninguna | N10: Probado con éxito mediante WiFi y cable Ethernet.
A11: 5 | B11: DMT Tool | C11: Ofimática y colaboración | D11: Global | E11: https://apps.powerapps.com/ | F11: Probado | G11: OK | H11: OK | I11: =IF($B11="","",IF($F11="No aplica","No aplica",IF(AND($G11="OK",$H11="OK"),"Acceso total (WiFi + Cable)",IF(AND($G11="OK",$H11<>"OK"),"Solo WiFi",IF(AND($H11="OK",$G11<>"OK"),"Solo cable Ethernet",IF(AND($G11="KO",$H11="KO"),"Sin acceso","Pendiente")))))) -> Acceso total (WiFi + Cable) | J11: Media | M11: Ninguna | N11: Probado con éxito mediante WiFi y cable Ethernet.
A12: 6 | B12: SERES Tool | C12: Facturación electrónica | D12: España | E12: https://miacceso.e-factura.net/ | F12: Probado | G12: OK | H12: OK | I12: =IF($B12="","",IF($F12="No aplica","No aplica",IF(AND($G12="OK",$H12="OK"),"Acceso total (WiFi + Cable)",IF(AND($G12="OK",$H12<>"OK"),"Solo WiFi",IF(AND($H12="OK",$G12<>"OK"),"Solo cable Ethernet",IF(AND($G12="KO",$H12="KO"),"Sin acceso","Pendiente")))))) -> Acceso total (WiFi + Cable) | J12: Alta | M12: Ninguna | N12: Probado con éxito mediante WiFi y cable Ethernet.
A13: 7 | B13: Acceso remoto a RSVGEST (escritorio) | C13: Escritorio remoto | D13: España (Tavernes Madera) | E13: Escritorio remoto al PC de Tavernes Madera | F13: Pendiente de instalación | G13: No probado | H13: No probado | I13: =IF($B13="","",IF($F13="No aplica","No aplica",IF(AND($G13="OK",$H13="OK"),"Acceso total (WiFi + Cable)",IF(AND($G13="OK",$H13<>"OK"),"Solo WiFi",IF(AND($H13="OK",$G13<>"OK"),"Solo cable Ethernet",IF(AND($G13="KO",$H13="KO"),"Sin acceso","Pendiente")))))) -> Pendiente | J13: Alta | M13: Instalar / Configurar | N13: Pendiente de instalación para poder probarlo.
A14: 8 | B14: Gestión PDF — descarga de facturas SERES | C14: Facturación electrónica | D14: España | E14: Aplicación de escritorio (descarga de PDF desde SERES) | F14: Pendiente de instalación | G14: No probado | H14: No probado | I14: =IF($B14="","",IF($F14="No aplica","No aplica",IF(AND($G14="OK",$H14="OK"),"Acceso total (WiFi + Cable)",IF(AND($G14="OK",$H14<>"OK"),"Solo WiFi",IF(AND($H14="OK",$G14<>"OK"),"Solo cable Ethernet",IF(AND($G14="KO",$H14="KO"),"Sin acceso","Pendiente")))))) -> Pendiente | J14: Alta | M14: Instalar / Configurar | N14: Pendiente de instalación para poder probarlo.
A15: 9 | B15: My Access | C15: Ofimática y colaboración | D15: Global | E15: https://myaccess.ipaper.com/ | F15: Probado | G15: OK | H15: OK | I15: =IF($B15="","",IF($F15="No aplica","No aplica",IF(AND($G15="OK",$H15="OK"),"Acceso total (WiFi + Cable)",IF(AND($G15="OK",$H15<>"OK"),"Solo WiFi",IF(AND($H15="OK",$G15<>"OK"),"Solo cable Ethernet",IF(AND($G15="KO",$H15="KO"),"Sin acceso","Pendiente")))))) -> Acceso total (WiFi + Cable) | J15: Media | M15: Ninguna | N15: Probado con éxito mediante WiFi y cable Ethernet.
A16: 10 | B16: OCR | C16: Cuentas a pagar (Matchpay) | D16: EMEA | E16: https://ocr.emea.ipaper.com/ | F16: Probado | G16: KO | H16: KO | I16: =IF($B16="","",IF($F16="No aplica","No aplica",IF(AND($G16="OK",$H16="OK"),"Acceso total (WiFi + Cable)",IF(AND($G16="OK",$H16<>"OK"),"Solo WiFi",IF(AND($H16="OK",$G16<>"OK"),"Solo cable Ethernet",IF(AND($G16="KO",$H16="KO"),"Sin acceso","Pendiente")))))) -> Sin acceso | J16: Alta | M16: Solicitar acceso a IT | N16: Sin acceso ni por WiFi ni por cable.
A17: 11 | B17: ECM | C17: Cuentas a pagar (Matchpay) | D17: EMEA | E17: https://ecm.emea.ipaper.com/ | F17: Probado | G17: OK | H17: OK | I17: =IF($B17="","",IF($F17="No aplica","No aplica",IF(AND($G17="OK",$H17="OK"),"Acceso total (WiFi + Cable)",IF(AND($G17="OK",$H17<>"OK"),"Solo WiFi",IF(AND($H17="OK",$G17<>"OK"),"Solo cable Ethernet",IF(AND($G17="KO",$H17="KO"),"Sin acceso","Pendiente")))))) -> Acceso total (WiFi + Cable) | J17: Alta | M17: Ninguna | N17: Con acceso tanto por WiFi como por cable.
A18: 12 | B18: Xelix | C18: Cuentas a pagar (Matchpay) | D18: Global | E18: https://ap.xelix.com/login | F18: Probado | G18: OK | H18: OK | I18: =IF($B18="","",IF($F18="No aplica","No aplica",IF(AND($G18="OK",$H18="OK"),"Acceso total (WiFi + Cable)",IF(AND($G18="OK",$H18<>"OK"),"Solo WiFi",IF(AND($H18="OK",$G18<>"OK"),"Solo cable Ethernet",IF(AND($G18="KO",$H18="KO"),"Sin acceso","Pendiente")))))) -> Acceso total (WiFi + Cable) | J18: Alta | M18: Ninguna | N18: Con acceso tanto por WiFi como por cable.
... A23: 17 | B23: Arrows (CARPA) | C23: CARPA | D23: España (CARPA) | E23: Acceso mediante escritorio remoto | F23: Probado | G23: KO | H23: KO | I23: =IF($B23="","",IF($F23="No aplica","No aplica",IF(AND($G23="OK",$H23="OK"),"Acceso total (WiFi + Cable)",IF(AND($G23="OK",$H23<>"OK"),"Solo WiFi",IF(AND($H23="OK",$G23<>"OK"),"Solo cable Ethernet",IF(AND($G23="KO",$H23="KO"),"Sin acceso","Pendiente")))))) -> Sin acceso | J23: Alta | M23: Solicitar acceso a IT | N23: Sin acceso ni por WiFi ni por cable.
A24: =IF($B24="","",ROW()-6) | I24: =IF($B24="","",IF($F24="No aplica","No aplica",IF(AND($G24="OK",$H24="OK"),"Acceso total (WiFi + Cable)",IF(AND($G24="OK",$H24<>"OK"),"Solo WiFi",IF(AND($H24="OK",$G24<>"OK"),"Solo cable Ethernet",IF(AND($G24="KO",$H24="KO"),"Sin acceso","Pendiente"))))))
A25: =IF($B25="","",ROW()-6) | I25: =IF($B25="","",IF($F25="No aplica","No aplica",IF(AND($G25="OK",$H25="OK"),"Acceso total (WiFi + Cable)",IF(AND($G25="OK",$H25<>"OK"),"Solo WiFi",IF(AND($H25="OK",$G25<>"OK"),"Solo cable Ethernet",IF(AND($G25="KO",$H25="KO"),"Sin acceso","Pendiente"))))))
A26: =IF($B26="","",ROW()-6) | I26: =IF($B26="","",IF($F26="No aplica","No aplica",IF(AND($G26="OK",$H26="OK"),"Acceso total (WiFi + Cable)",IF(AND($G26="OK",$H26<>"OK"),"Solo WiFi",IF(AND($H26="OK",$G26<>"OK"),"Solo cable Ethernet",IF(AND($G26="KO",$H26="KO"),"Sin acceso","Pendiente"))))))
A27: =IF($B27="","",ROW()-6) | I27: =IF($B27="","",IF($F27="No aplica","No aplica",IF(AND($G27="OK",$H27="OK"),"Acceso total (WiFi + Cable)",IF(AND($G27="OK",$H27<>"OK"),"Solo WiFi",IF(AND($H27="OK",$G27<>"OK"),"Solo cable Ethernet",IF(AND($G27="KO",$H27="KO"),"Sin acceso","Pendiente"))))))
A28: =IF($B28="","",ROW()-6) | I28: =IF($B28="","",IF($F28="No aplica","No aplica",IF(AND($G28="OK",$H28="OK"),"Acceso total (WiFi + Cable)",IF(AND($G28="OK",$H28<>"OK"),"Solo WiFi",IF(AND($H28="OK",$G28<>"OK"),"Solo cable Ethernet",IF(AND($G28="KO",$H28="KO"),"Sin acceso","Pendiente"))))))
A29: =IF($B29="","",ROW()-6) | I29: =IF($B29="","",IF($F29="No aplica","No aplica",IF(AND($G29="OK",$H29="OK"),"Acceso total (WiFi + Cable)",IF(AND($G29="OK",$H29<>"OK"),"Solo WiFi",IF(AND($H29="OK",$G29<>"OK"),"Solo cable Ethernet",IF(AND($G29="KO",$H29="KO"),"Sin acceso","Pendiente"))))))
A30: =IF($B30="","",ROW()-6) | I30: =IF($B30="","",IF($F30="No aplica","No aplica",IF(AND($G30="OK",$H30="OK"),"Acceso total (WiFi + Cable)",IF(AND($G30="OK",$H30<>"OK"),"Solo WiFi",IF(AND($H30="OK",$G30<>"OK"),"Solo cable Ethernet",IF(AND($G30="KO",$H30="KO"),"Sin acceso","Pendiente"))))))
A31: =IF($B31="","",ROW()-6) | I31: =IF($B31="","",IF($F31="No aplica","No aplica",IF(AND($G31="OK",$H31="OK"),"Acceso total (WiFi + Cable)",IF(AND($G31="OK",$H31<>"OK"),"Solo WiFi",IF(AND($H31="OK",$G31<>"OK"),"Solo cable Ethernet",IF(AND($G31="KO",$H31="KO"),"Sin acceso","Pendiente"))))))
A32: =IF($B32="","",ROW()-6) | I32: =IF($B32="","",IF($F32="No aplica","No aplica",IF(AND($G32="OK",$H32="OK"),"Acceso total (WiFi + Cable)",IF(AND($G32="OK",$H32<>"OK"),"Solo WiFi",IF(AND($H32="OK",$G32<>"OK"),"Solo cable Ethernet",IF(AND($G32="KO",$H32="KO"),"Sin acceso","Pendiente"))))))
A33: =IF($B33="","",ROW()-6) | I33: =IF($B33="","",IF($F33="No aplica","No aplica",IF(AND($G33="OK",$H33="OK"),"Acceso total (WiFi + Cable)",IF(AND($G33="OK",$H33<>"OK"),"Solo WiFi",IF(AND($H33="OK",$G33<>"OK"),"Solo cable Ethernet",IF(AND($G33="KO",$H33="KO"),"Sin acceso","Pendiente"))))))
A35: FILA DE EJEMPLO — muestra el formato esperado al dar de alta un sistema nuevo. No se contabiliza en la hoja «Resumen»; escriba los sistemas nuevos en las filas libres de la tabla de arriba.
A36: 18 | B36: Nombre del sistema | C36: Área funcional | D36: España | E36: https://ejemplo.ipaper.com/ | F36: Probado | G36: OK | H36: KO | I36: Solo WiFi | J36: Alta | K36: Nombre y apellidos | L36: 12/08/2026 | M36: Escalar a IT / Redes | N36: Acceso correcto por WiFi; por cable Ethernet devuelve tiempo de espera agotado.
A38: NOTAS Y SUPUESTOS
A39: • Fuente de los datos: listado «SAP E01 – Pendiente de prueba» facilitado por el usuario. Los estados y resultados de WiFi/cable reproducen literalmente ese listado.
A40: • «Criticidad»: propuesta inicial elaborada al construir este libro; NO figuraba en el listado de origen. Revísela y ajústela.
A41: • «Sage — acceso a Adonix (CARPA)» aparecía dos veces en el listado de origen (bloques 1 y 2) con idéntico resultado: se ha consolidado en una sola fila (N.º 3). Por eso el libro recoge 17 sistemas y no 18.
A42: • «Accounts Payable (Matchpay)» no traía URL en el listado de origen; queda pendiente de confirmar.
A43: • «Responsable» y «Fecha de prueba» se dejan en blanco a propósito, para que los complete quien realice las pruebas.
A44: • Todo lo que se escriba en las filas libres de la tabla se suma automáticamente a los indicadores de la hoja «Resumen».

Sheet Listas
B2: LISTAS DE VALORES DE LOS DESPLEGABLES
B3: Puede añadir o modificar valores en estas columnas: los desplegables de la hoja «Seguimiento» se actualizan automáticamente. No borre las cabeceras.
B5: Estado de la prueba | C5: Próxima acción | D5: WiFi / Cable | E5: Criticidad | F5: Resultado (calculado)
B6: Pendiente de prueba | C6: Ninguna | D6: OK | E6: Crítica | F6: Acceso total (WiFi + Cable)
B7: Pendiente de instalación | C7: Programar prueba | D7: KO | E7: Alta | F7: Solo WiFi
B8: En curso | C8: Instalar / Configurar | D8: No probado | E8: Media | F8: Solo cable Ethernet
B9: Probado | C9: Solicitar acceso a IT | D9: N/A | E9: Baja | F9: Sin acceso
B10: No aplica | C10: Escalar a IT / Redes | F10: Pendiente
C11: Revisar VPN / Firewall | F11: No aplica
C12: Reprogramar prueba
C13: En seguimiento
